CHANGELOG.rst
MANIFEST.in
README.rst
setup.cfg
setup.py
playground_metrics/__init__.py
playground_metrics/map_metric.py
playground_metrics/match_detections.py
playground_metrics.egg-info/PKG-INFO
playground_metrics.egg-info/SOURCES.txt
playground_metrics.egg-info/dependency_links.txt
playground_metrics.egg-info/not-zip-safe
playground_metrics.egg-info/requires.txt
playground_metrics.egg-info/top_level.txt
playground_metrics/metrics_helper/__init__.py
playground_metrics/metrics_helper/mean_fbeta.py
playground_metrics/utils/__init__.py
playground_metrics/utils/deprecation_utils.py
playground_metrics/utils/exception.py
playground_metrics/utils/iou_utils.py
playground_metrics/utils/geometry_utils/__init__.py
playground_metrics/utils/geometry_utils/base_geometry.py
playground_metrics/utils/geometry_utils/geometry.py