Metadata-Version: 2.1
Name: playground-metrics
Version: 1.0.1
Summary: Playground framework agnostic detection mAP scoring library.
Home-page: https://github.com/airbusgeo/playground-metrics
Author: Airbus DS GEO
Author-email: jeffaudi.airbus@gmail.com
License: MIT
Platform: UNKNOWN
Classifier: Development Status :: 5 - Production/Stable
Classifier: Intended Audience :: Developers
Classifier: License :: OSI Approved :: MIT License
Classifier: Programming Language :: Python
Classifier: Programming Language :: Python :: 3
Classifier: Programming Language :: Python :: 3.6
Classifier: Programming Language :: Python :: 3.7
Classifier: Programming Language :: Python :: 3.8
Classifier: Programming Language :: Python :: 3.9
Classifier: Programming Language :: Python :: Implementation :: CPython
Requires-Python: >=3.6
Provides-Extra: docs
Provides-Extra: lint
Provides-Extra: tests
Provides-Extra: tests_visualisation_utility
